{"code":"0000","message":"成功---success","data":{"item":[{"boy_rate":"69","degree":"","fivesalaryavg":8000,"girl_rate":"31","hightitle":"通信工程设计与监理","id":"gkspecial800","level1":"2","level1_name":"专科（高职）","level2":"25","level2_name":"电子与信息大类","level3":"184","level3_name":"通信类","limit_year":"三年","name":"通信工程设计与监理","rank":"297","salaryavg":131263,"spcode":"510305","special_id":"800","view_month":"121","view_total":"418286","view_week":"121"},{"boy_rate":"63","degree":"","fivesalaryavg":7600,"girl_rate":"37","hightitle":"通信系统运行管理","id":"gkspecial799","level1":"2","level1_name":"专科（高职）","level2":"25","level2_name":"电子与信息大类","level3":"184","level3_name":"通信类","limit_year":"三年","name":"通信系统运行管理","rank":"298","salaryavg":130299,"spcode":"510306","special_id":"799","view_month":"67","view_total":"110608","view_week":"67"},{"boy_rate":"0","degree":"","fivesalaryavg":8100,"girl_rate":"0","hightitle":"智能互联网络技术","id":"gkspecial9069","level1":"2","level1_name":"专科（高职）","level2":"25","level2_name":"电子与信息大类","level3":"184","level3_name":"通信类","limit_year":"三年","name":"智能互联网络技术","rank":"0","salaryavg":154278,"spcode":"510307","special_id":"9069","view_month":"206","view_total":"32860","view_week":"206"},{"boy_rate":"0","degree":"","fivesalaryavg":0,"girl_rate":"0","hightitle":"网络规划与优化技术","id":"gkspecial9070","level1":"2","level1_name":"专科（高职）","level2":"25","level2_name":"电子与信息大类","level3":"184","level3_name":"通信类","limit_year":"三年","name":"网络规划与优化技术","rank":"0","salaryavg":130333,"spcode":"510308","special_id":"9070","view_month":"37","view_total":"23287","view_week":"37"},{"boy_rate":"23","degree":"","fivesalaryavg":6600,"girl_rate":"77","hightitle":"电信服务与管理","id":"gkspecial1097","level1":"2","level1_name":"专科（高职）","level2":"25","level2_name":"电子与信息大类","level3":"184","level3_name":"通信类","limit_year":"三年","name":"电信服务与管理","rank":"296","salaryavg":130312,"spcode":"510309","special_id":"1097","view_month":"95","view_total":"348497","view_week":"95"},{"boy_rate":"0","degree":"","fivesalaryavg":0,"girl_rate":"0","hightitle":"集成电路技术","id":"gkspecial9071","level1":"2","level1_name":"专科（高职）","level2":"25","level2_name":"电子与信息大类","level3":"228","level3_name":"集成电路类","limit_year":"三年","name":"集成电路技术","rank":"0","salaryavg":98113,"spcode":"510401","special_id":"9071","view_month":"629","view_total":"39763","view_week":"629"},{"boy_rate":"76","degree":"","fivesalaryavg":8500,"girl_rate":"24","hightitle":"微电子技术","id":"gkspecial766","level1":"2","level1_name":"专科（高职）","level2":"25","level2_name":"电子与信息大类","level3":"228","level3_name":"集成电路类","limit_year":"三年","name":"微电子技术","rank":"331","salaryavg":97916,"spcode":"510402","special_id":"766","view_month":"346","view_total":"149501","view_week":"346"}],"numFound":37},"location":"","encrydata":""}